{
  "HELP_DESC": "Запись сообщенія въ базу для канала",
  "SUCCESS": "предоставленное Вами высказываніе было успѣшно записано въ базу и прикрѣплено къ данному каналу ",
  "FAIL": "не удалось сохранить высказываніе",
  "READ": "чтеніе сообщеній уже включено для даннаго канала, сохраненіе отмѣнено",
  "USAGE_EXAMPLE_1": "Добавить высказываніе \"hello\" въ исторію сообщеній даннаго канала",
  "USAGE_EXAMPLE_2": "Получить контентъ предоставленнаго файла и сохранить въ исторію сообщеній этого канала",
  "PASTE_FAIL": "не удалось получить контентъ изъ предоставленнаго файла",
  "PASTE_LARGE": "предоставленный текстъ слишкомъ большой (максимальное количество символовъ - %limit%)",
  "PASTE_COOLDOWN": "ты можешь добавить сообщенія изъ файла только %date%"
}