{
	"HELP_DESC": "ИНФА О ввыфшг GENAI PREMIUM",
	"INFO_TITLE": "паста про о geni preminm.",
	"USAGE_EXAMPLE_1": "показ ИНФЫ о gen prem.",
	"USAGE_EXAMPLE_2": "показать сераырив где ты врубил эти нуу бонусы",
	"USAGE_EXAMPLE_3": "оформить вкид для этого сервера",
	"INFO_DESCRIPTION": "ну ты это аваыв можешь кинуть донат и получить приколы смешнявки да короч ..",
	"INFO_DESCRIPTION_PURCHASE": "где купить епта . в **[patroen](https://genai.altir.xyz/premium)** наверн",
	"INFO_PERKS_TITLE": "че дает",
	"INFO_PERKS_LIST": [
		"актив (нет блин пассив) приколов для **%limit% серевроиа**",
		"кд на ген команды будт меньше на **40%**",
		"интварл автопука будет **от 5 сообщ** !! `%prefix%interval <5-50>`",
		"genai **autogen DEMOTIVATOR** gggggg ! `%prefix%autogen`",
		"ебааа **можно продолжать приколы**! `%prefix%generate <вставляй пасту епта>)`",
		"будет теперь **10 фильтров на канал** епта а аа "
	],
	"GUILDS_NO_PREMIUM": "мда чел купи подпис очку в `%prefix%premium`",
	"GUILDS_NO_ITEMS": "челик активируй бусты ну хоть гденибдьбь пж =))",
	"GUILDS_LIST_TITLE": "ГДЕ ЕСТЬ АКТИВИРОВАННЫЙ SNUS GENAI PREMIUM",
	"TOGGLE_NO_PREMIUM": "челище купи премиму . .. тут! `%prefix%premium`",
	"TOGGLE_ANOTHER_ACTIVATED": "не повезл ... ктот уже активировал тут приколы",
	"TOGGLE_LIMIT": "челик чет много серверов ты активировал, отклбчи гденибдьь =)",
	"TOGGLE_UNKNOWN_ERROR": "чет не получилосб",
	"TOGGLE_ENABLED": "xapowxapowxapow включил приколы !",
	"TOGGLE_DISABLED": "ну ладн не будет тут eliteSNUS"
}